mal/__init__.py
mal/anime.py
mal/mal.py
mal/resources.py
mal_parser-0.0.1.dist-info/METADATA
mal_parser-0.0.1.dist-info/WHEEL
mal_parser-0.0.1.dist-info/top_level.txt
mal_parser-0.0.1.dist-info/RECORD
