Metadata-Version: 2.1
Name: mal-parser
Version: 0.0.1
Summary: An mal parser package
Home-page: UNKNOWN
Author: Kira99
Author-email: shohanduttaroy99@gmail.com
License: UNKNOWN
Platform: UNKNOWN
Classifier: Programming Language :: Python :: 3
Classifier: License :: OSI Approved :: MIT License
Classifier: Operating System :: OS Independent
